TextGenerator/GenerateText.py
TextGenerator/PrepareChain.py
TextGenerator/__init__.py
TextGenerator/main.py
TextGenerator_cli-0.1.7.dist-info/METADATA
TextGenerator_cli-0.1.7.dist-info/WHEEL
TextGenerator_cli-0.1.7.dist-info/entry_points.txt
TextGenerator_cli-0.1.7.dist-info/top_level.txt
TextGenerator_cli-0.1.7.dist-info/RECORD
