Metadata-Version: 2.1
Name: TextGenerator-cli
Version: 0.1.7
Summary: マルコフ連鎖を使った文章自動生成プログラム+CLI
Home-page: https://github.com/eggplants/TextGenerator-cli
Author: eggplants
License: MIT
Platform: UNKNOWN
Requires-Python: >=3.5
Requires-Dist: chardet
Requires-Dist: mecab-python3
